{"cameraMode":{"drawMode":1,"name":"Wireframe","section":"Shading Mode"},"sceneLighting":true,"audioPlay":false,"sceneViewState":{"m_AlwaysRefresh":false,"showFog":true,"showSkybox":true,"showFlares":true,"showImageEffects":true,"showParticleSystems":true,"showVisualEffectGraphs":true,"m_FxEnabled":true},"in2DMode":false,"pivot":{"x":-31.246084213256837,"y":-115.73090362548828,"z":93.16777038574219},"rotation":{"x":-0.43837061524391177,"y":0.1864890158176422,"z":-0.09379507601261139,"w":-0.8745474219322205},"size":91.92388153076172,"orthographic":false}